[
    {
        "imagePath": "https://productimages.hepsiburada.net/s/5/200/9679093858354.jpg",
        "title": "Xiaomi Mi Band 4 Akıllı Bileklik Siyah",
        "rate": 4,
        "commentCount": 15,
        "id": 1
    },
    {
        "imagePath": "https://productimages.hepsiburada.net/s/5/200/9679093858354.jpg",
        "title": "Xiaomi Mi Band 5 Akıllı Bileklik Siyah",
        "rate": 5,
        "commentCount": 4,
        "id": 5
    },
    {
        "imagePath": "https://productimages.hepsiburada.net/s/5/200/9679093858354.jpg",
        "title": "Xiaomi Mi Band 2 Akıllı Bileklik Siyah",
        "rate": 2,
        "commentCount": 55,
        "id": 3
    }
]
